mtrayapp/__init__.py
mtrayapp/_appindicator.py
mtrayapp/_base.py
mtrayapp/_darwin.py
mtrayapp/_dummy.py
mtrayapp/_win32.py
mtrayapp/_util/__init__.py
mtrayapp/_util/gtk.py
mtrayapp/_util/notify_dbus.py
mtrayapp/_util/win32.py
mtrayapp-1.0.2.dist-info/COPYING
mtrayapp-1.0.2.dist-info/COPYING.LGPL
mtrayapp-1.0.2.dist-info/METADATA
mtrayapp-1.0.2.dist-info/WHEEL
mtrayapp-1.0.2.dist-info/top_level.txt
mtrayapp-1.0.2.dist-info/zip-safe
mtrayapp-1.0.2.dist-info/RECORD
